MANIFEST.in
README.rst
install.sh
requirements.txt
setup.cfg
setup.py
gat/Bed.py
gat/CoordinateList.pxd
gat/CoordinateList.pyx
gat/Engine.pxd
gat/Engine.pyx
gat/Experiment.py
gat/IO.py
gat/IOTools.py
gat/PointList.pyx
gat/PositionList.pxd
gat/PositionList.pyx
gat/SegmentList.pxd
gat/SegmentList.pyx
gat/Stats.py
gat/__init__.py
gat.egg-info/PKG-INFO
gat.egg-info/SOURCES.txt
gat.egg-info/dependency_links.txt
gat.egg-info/not-zip-safe
gat.egg-info/requires.txt
gat.egg-info/top_level.txt
scripts/gat-compare.py
scripts/gat-great.py
scripts/gat-plot.py
scripts/gat-run.py
test/test_PositionList.py
test/test_SegmentList.py
test/test_gat.py
test/test_gat_stats.py
utils/gat_utils.c
utils/gat_utils.h