Metadata-Version: 1.0
Name: gat
Version: 1.3.6
Summary: GenomicAssocationTester
Home-page: https://github.com/AndreasHeger/gat
Author: Andreas Heger
Author-email: andreas.heger@gmail.com
License: MIT
Platform: ALL
